<?xml version="1.0" encoding="utf-8" ?>
<LanguageData>

 <Playwright.Components.Origins.Compat_VREAndroids_Androids>Androids</Playwright.Components.Origins.Compat_VREAndroids_Androids>
 <Playwright.Components.Origins.Compat_VREAndroids_Androids.Description>(TODO) Androids hoping to create a new utopia for themselves and their kind. News of their efforts will spread far and wide. Can you handle the influx of newcomers?</Playwright.Components.Origins.Compat_VREAndroids_Androids.Description>
 <Playwright.Components.Origins.Compat_VREAndroids_Androids.Description.Short>Androids hoping to create a new utopia for themselves and their kind.</Playwright.Components.Origins.Compat_VREAndroids_Androids.Description.Short>
 <Playwright.Components.Origins.Compat_VREAndroids_Androids.Summary>- Choose 3 colonists (out of 10)
- Every starting colonist is an Android.
- You will get an influx of Android refugees every so often.
- Start with some basic supplies.
- Random junk like steel and wood is scattered around the map.</Playwright.Components.Origins.Compat_VREAndroids_Androids.Summary>
 <Playwright.Components.Origins.Compat_VREAndroids_Androids.SuggestedIdeo>Egalitarian</Playwright.Components.Origins.Compat_VREAndroids_Androids.SuggestedIdeo>

</LanguageData>
